{
  "moduleId": "M17-machine-monitoring-andon",
  "moduleName": "Giám sát máy và Andon",
  "route": "/mes/monitoring/andon",
  "primaryEntity": "machineStatus",
  "endpoints": [
    {
      "alias": "m17.machine.monitoring.andon.list",
      "method": "POST",
      "path": "/mes/monitoring/andon/query",
      "interactionType": "query",
      "ownerSystem": "MES",
      "systemOfRecord": "MOM",
      "requiresOnline": false,
      "idempotency": "not-required",
      "freshnessPolicy": "machine-heartbeat",
      "permission": "andon.read",
      "auditEvent": "QueryExecuted",
      "offlinePolicy": "allowed",
      "errorContract": [
        "validation",
        "permission-denied",
        "conflict",
        "timeout",
        "stale-source"
      ],
      "request": {
        "filters": [
          "field/operator/value"
        ],
        "sort": [
          "field,dir"
        ],
        "page": {
          "number": "int",
          "size": "int"
        },
        "viewId": "optional saved view"
      },
      "response": {
        "rows": [
          "machineStatus summary row"
        ],
        "total": "int",
        "aggregates": "optional kpi totals"
      }
    },
    {
      "alias": "m17.machine.monitoring.andon.detail",
      "method": "GET",
      "path": "/mes/monitoring/andon/{id}",
      "interactionType": "query",
      "ownerSystem": "MES",
      "systemOfRecord": "MOM",
      "requiresOnline": false,
      "idempotency": "not-required",
      "freshnessPolicy": "machine-heartbeat",
      "permission": "andon.read",
      "auditEvent": "DetailViewed",
      "offlinePolicy": "allowed",
      "errorContract": [
        "validation",
        "permission-denied",
        "conflict",
        "timeout",
        "stale-source"
      ],
      "request": {
        "id": "string path param",
        "include": [
          "tabs or related datasets"
        ]
      },
      "response": {
        "record": "machineStatus detail",
        "related": "context datasets",
        "auditPreview": "last events"
      }
    },
    {
      "alias": "m17.machine.monitoring.andon.lookup",
      "method": "POST",
      "path": "/mes/monitoring/andon/lookup",
      "interactionType": "lookup",
      "ownerSystem": "MES",
      "systemOfRecord": "MOM",
      "requiresOnline": false,
      "idempotency": "not-required",
      "freshnessPolicy": "machine-heartbeat",
      "permission": "andon.read",
      "auditEvent": "LookupUsed",
      "offlinePolicy": "allowed",
      "errorContract": [
        "validation",
        "permission-denied",
        "conflict",
        "timeout",
        "stale-source"
      ],
      "request": {
        "search": "string",
        "limit": "int",
        "filters": "optional lightweight filters"
      },
      "response": {
        "options": [
          {
            "id": "string",
            "label": "string",
            "status": "string"
          }
        ]
      }
    },
    {
      "alias": "m17.machine.monitoring.andon.metrics",
      "method": "GET",
      "path": "/mes/monitoring/andon/metrics",
      "interactionType": "query",
      "ownerSystem": "MES",
      "systemOfRecord": "MOM",
      "requiresOnline": false,
      "idempotency": "not-required",
      "freshnessPolicy": "machine-heartbeat",
      "permission": "andon.read",
      "auditEvent": "MetricsViewed",
      "offlinePolicy": "allowed",
      "errorContract": [
        "validation",
        "permission-denied",
        "conflict",
        "timeout",
        "stale-source"
      ],
      "request": {
        "timeWindow": "optional",
        "groupBy": "optional"
      },
      "response": {
        "kpis": "named KPI set",
        "timestamp": "source timestamp"
      }
    },
    {
      "alias": "m17.machine.monitoring.andon.update",
      "method": "PATCH",
      "path": "/mes/monitoring/andon/{id}",
      "interactionType": "command",
      "ownerSystem": "MES",
      "systemOfRecord": "MOM",
      "requiresOnline": true,
      "idempotency": "conditional",
      "freshnessPolicy": "machine-heartbeat",
      "permission": "andon.assign",
      "auditEvent": "RecordUpdated",
      "offlinePolicy": "forbidden",
      "errorContract": [
        "validation",
        "permission-denied",
        "conflict",
        "timeout",
        "stale-source"
      ],
      "request": {
        "id": "string path param",
        "etag": "If-Match value",
        "patch": "changed fields only",
        "reasonCode": "required when controlled"
      },
      "response": {
        "id": "record id",
        "status": "current workflow state",
        "etag": "new version token"
      }
    },
    {
      "alias": "m17.machine.monitoring.andon.command.acknowledge-alarm",
      "method": "POST",
      "path": "/mes/monitoring/andon/{id}/actions/acknowledge-alarm",
      "interactionType": "workflow-transition",
      "ownerSystem": "MES",
      "systemOfRecord": "MOM",
      "requiresOnline": true,
      "idempotency": "required",
      "freshnessPolicy": "machine-heartbeat",
      "permission": "andon.acknowledge",
      "auditEvent": "AcknowledgeAlarmRequested",
      "offlinePolicy": "forbidden",
      "errorContract": [
        "validation",
        "permission-denied",
        "conflict",
        "timeout",
        "stale-source"
      ],
      "request": {
        "id": "string path param",
        "reasonCode": "required for hold/reject/disposition/void where applicable",
        "comment": "optional user note",
        "payload": "command-specific fields"
      },
      "response": {
        "id": "record id",
        "status": "new workflow state",
        "taskRefs": "downstream/generated tasks if any"
      }
    },
    {
      "alias": "m17.machine.monitoring.andon.command.shelve-alarm",
      "method": "POST",
      "path": "/mes/monitoring/andon/{id}/actions/shelve-alarm",
      "interactionType": "workflow-transition",
      "ownerSystem": "MES",
      "systemOfRecord": "MOM",
      "requiresOnline": true,
      "idempotency": "required",
      "freshnessPolicy": "machine-heartbeat",
      "permission": "andon.shelve",
      "auditEvent": "ShelveAlarmRequested",
      "offlinePolicy": "forbidden",
      "errorContract": [
        "validation",
        "permission-denied",
        "conflict",
        "timeout",
        "stale-source"
      ],
      "request": {
        "id": "string path param",
        "reasonCode": "required for hold/reject/disposition/void where applicable",
        "comment": "optional user note",
        "payload": "command-specific fields"
      },
      "response": {
        "id": "record id",
        "status": "new workflow state",
        "taskRefs": "downstream/generated tasks if any"
      }
    },
    {
      "alias": "m17.machine.monitoring.andon.command.assign-response",
      "method": "POST",
      "path": "/mes/monitoring/andon/{id}/actions/assign-response",
      "interactionType": "workflow-transition",
      "ownerSystem": "MES",
      "systemOfRecord": "MOM",
      "requiresOnline": true,
      "idempotency": "required",
      "freshnessPolicy": "machine-heartbeat",
      "permission": "andon.assign",
      "auditEvent": "AssignResponseRequested",
      "offlinePolicy": "forbidden",
      "errorContract": [
        "validation",
        "permission-denied",
        "conflict",
        "timeout",
        "stale-source"
      ],
      "request": {
        "id": "string path param",
        "reasonCode": "required for hold/reject/disposition/void where applicable",
        "comment": "optional user note",
        "payload": "command-specific fields"
      },
      "response": {
        "id": "record id",
        "status": "new workflow state",
        "taskRefs": "downstream/generated tasks if any"
      }
    },
    {
      "alias": "m17.machine.monitoring.andon.command.open-detail",
      "method": "POST",
      "path": "/mes/monitoring/andon/{id}/actions/open-detail",
      "interactionType": "workflow-transition",
      "ownerSystem": "MES",
      "systemOfRecord": "MOM",
      "requiresOnline": true,
      "idempotency": "required",
      "freshnessPolicy": "machine-heartbeat",
      "permission": "andon.assign",
      "auditEvent": "OpenDetailRequested",
      "offlinePolicy": "forbidden",
      "errorContract": [
        "validation",
        "permission-denied",
        "conflict",
        "timeout",
        "stale-source"
      ],
      "request": {
        "id": "string path param",
        "reasonCode": "required for hold/reject/disposition/void where applicable",
        "comment": "optional user note",
        "payload": "command-specific fields"
      },
      "response": {
        "id": "record id",
        "status": "new workflow state",
        "taskRefs": "downstream/generated tasks if any"
      }
    },
    {
      "alias": "m17.machine.monitoring.andon.export",
      "method": "POST",
      "path": "/mes/monitoring/andon/export",
      "interactionType": "export",
      "ownerSystem": "MES",
      "systemOfRecord": "MOM",
      "requiresOnline": false,
      "idempotency": "required",
      "freshnessPolicy": "machine-heartbeat",
      "permission": "andon.export",
      "auditEvent": "ExportRequested",
      "offlinePolicy": "allowed",
      "errorContract": [
        "validation",
        "permission-denied",
        "conflict",
        "timeout",
        "stale-source"
      ],
      "request": {
        "format": "pdf|xlsx|csv|zip",
        "filters": "same as list scope",
        "columns": "optional",
        "includeAudit": "bool for regulated"
      },
      "response": {
        "jobId": "export job id",
        "downloadRef": "when synchronous or completed"
      }
    }
  ],
  "envelope": {
    "headers": {
      "X-Request-Id": "uuid",
      "X-User-Timezone": "IANA string",
      "If-Match": "etag for PATCH when concurrency controlled",
      "Idempotency-Key": "required for POST command endpoints"
    },
    "responseEnvelope": {
      "data": "payload",
      "meta": {
        "requestId": "uuid",
        "timestamp": "iso-8601",
        "freshness": "fresh|stale|expired"
      },
      "permissions": "action-level allow/deny flags",
      "errors": "structured error array when failed"
    }
  }
}