{
  "_meta": { "version": "1.0", "description": "Field type definitions — how each data type renders, formats, aligns, and edits" },
  "string":   { "icon": "Aa",  "format": null,           "align": "left",   "editable": true,  "filterType": "text",         "sortable": true },
  "number":   { "icon": "#",   "format": "number",       "align": "right",  "editable": true,  "filterType": "number-range", "sortable": true },
  "integer":  { "icon": "#",   "format": "integer",      "align": "right",  "editable": true,  "filterType": "number-range", "sortable": true },
  "currency": { "icon": "$",   "format": "currency",     "align": "right",  "editable": true,  "filterType": "number-range", "sortable": true },
  "percent":  { "icon": "%",   "format": "percent",      "align": "right",  "editable": true,  "filterType": "number-range", "sortable": true },
  "date":     { "icon": "📅",  "format": "date",         "align": "left",   "editable": true,  "filterType": "date-range",   "sortable": true },
  "datetime": { "icon": "🕐",  "format": "datetime",     "align": "left",   "editable": true,  "filterType": "date-range",   "sortable": true },
  "time":     { "icon": "⏰",  "format": "time",         "align": "left",   "editable": true,  "filterType": "text",         "sortable": true },
  "boolean":  { "icon": "✓",   "format": "boolean",      "align": "center", "editable": true,  "filterType": "boolean",      "sortable": true },
  "badge":    { "icon": "🏷",  "format": "badge",        "align": "center", "editable": false, "filterType": "select",       "sortable": true },
  "email":    { "icon": "✉",   "format": "email",        "align": "left",   "editable": true,  "filterType": "text",         "sortable": true },
  "phone":    { "icon": "📞",  "format": "phone",        "align": "left",   "editable": true,  "filterType": "text",         "sortable": false },
  "url":      { "icon": "🔗",  "format": "url",          "align": "left",   "editable": false, "filterType": "text",         "sortable": false },
  "image":    { "icon": "🖼",  "format": "image",        "align": "center", "editable": false, "filterType": null,           "sortable": false },
  "json":     { "icon": "{}",  "format": "json",         "align": "left",   "editable": true,  "filterType": null,           "sortable": false },
  "textarea": { "icon": "¶",   "format": "text",         "align": "left",   "editable": true,  "filterType": "text",         "sortable": false },
  "select":   { "icon": "▾",   "format": null,           "align": "left",   "editable": true,  "filterType": "select",       "sortable": true },
  "tags":     { "icon": "🏷",  "format": "tags",         "align": "left",   "editable": true,  "filterType": "text",         "sortable": false },
  "progress": { "icon": "█",   "format": "progress_bar", "align": "center", "editable": false, "filterType": "number-range", "sortable": true },
  "color":    { "icon": "🎨",  "format": "color_dot",    "align": "center", "editable": true,  "filterType": null,           "sortable": false },
  "duration": { "icon": "⏱",   "format": "duration",     "align": "right",  "editable": true,  "filterType": "number-range", "sortable": true },
  "weight":   { "icon": "⚖",   "format": "weight",       "align": "right",  "editable": true,  "filterType": "number-range", "sortable": true },
  "dimension":{ "icon": "📏",  "format": "dimension",    "align": "right",  "editable": true,  "filterType": "number-range", "sortable": true },
  "uuid":     { "icon": "🔑",  "format": "uuid",         "align": "left",   "editable": false, "filterType": "text",         "sortable": false },
  "code":     { "icon": "<>",  "format": "monospace",     "align": "left",   "editable": true,  "filterType": "text",         "sortable": true }
}
